PCF8591.py
pcf8591_library-0.0.3.dist-info/LICENSE.md
pcf8591_library-0.0.3.dist-info/METADATA
pcf8591_library-0.0.3.dist-info/WHEEL
pcf8591_library-0.0.3.dist-info/top_level.txt
pcf8591_library-0.0.3.dist-info/RECORD
