Metadata-Version: 2.1
Name: pcf8591-library
Version: 0.0.3
Summary: Library to use pcf8591 i2c analog IC with Arduino, Raspberry Pi Pico and rp2040 boards, esp32, SMT32 and ESP8266. Can read analog value and write analog value with only 2 wire. 
Home-page: https://github.com/xreef/PCF8591_micropython_library
Author: Renzo Mischianti
Author-email: Renzo Mischianti <renzo@mischianti.org>
Maintainer: Renzo Mischianti
Maintainer-email: Renzo Mischianti <renzo@mischianti.org>
License: The MIT License (MIT)
Project-URL: homepage, https://www.mischianti.org
Project-URL: Documentation, https://www.mischianti.org/2019/01/03/pcf8591-i2c-analog-i-o-expander/
Project-URL: Documentazione, https://www.mischianti.org/it/2019/01/03/pcf8591-un-expander-i2c-i-o-analogico/
Project-URL: Repository, https://github.com/xreef/PCF8591_micropython_library
Project-URL: Bug Tracker, https://github.com/xreef/PCF8591_micropython_library/issues
Project-URL: Examples, https://github.com/xreef/PCF8591_micropython_library/tree/master/examples
Keywords: micropython,analog, digital, i2c, encoder, expander, pcf8591, pcf8591a, esp32, esp8266, stm32, SAMD, Arduino, wire, Raspberry, rp2040
Classifier: Development Status :: 5 - Production/Stable
Classifier: Programming Language :: Python :: Implementation :: MicroPython
Classifier: License :: OSI Approved :: MIT License
Requires-Python: >=3.7
License-File: LICENSE.md
